{
    
    "errors": {
      "1001": {
        "description": "Cannot extract game file to ORIGINAL DISC",
        "type": "wit error"
      },
      "2001": {
        "description": "Invalid config.txt",
        "type": "config error"
      },
      "2002": {
        "description": "Cannot line in config.txt",
        "type": "config error"
      },
      "2003": {
        "description": "Wctct failed",
        "type": "config error"
      },
      "2101": {
        "description": "Invalid lpar.txt",
        "type": "lpar error"
      },
      "2201": {
        "description": "Cannot parse packID in XML",
        "type": "xml error"
      },
      "2202": {
        "description": "Cannot find XML file",
        "type": "xml error"
      },
      "3001": {
        "description": "Gecko code contains an invalid character",
        "type": "gecko error"
      },
      "2501": {
        "description": "Invalid cup png",
        "type": "cup image error"
      },
      "3002": {
        "description": "Gecko code is incompleted",
        "type": "gecko error"
      },
      "3003": {
        "description": "Gecko code .json not found in myCodes",
        "type": "gecko error"
      },
      "5501": {
        "description": "Normal BRSTM not found",
        "type": "custom music"
      },
      "5502": {
        "description": "Fast BRSTM not found",
        "type": "custom music"
      },
      "5503": {
        "description": "Cannot parse ffmpeg",
        "type": "custom music"
      },
      "5504": {
        "description": "BRSTM folder does not exist",
        "type": "custom music"
      },
      "7001": {
        "description": "Cannot copy icon to extracted folder",
        "type": "custom characters"
      },
      "7002": {
        "description": "Cannot write ctdm_settings.txt for custom character.",
        "type": "custom characters"
      }

    }
  }
  